multiplexer.v
`timescale 1ns/1ps
module mux21 #(parameter width = 5)(
    input sel,
    input [width-1:0]a,
    input [width-1:0]b,
    output reg [width-1:0]y
);
always @(*) begin
    case (sel)
        1'b0: y = a;
        1'b1: y = b;
        default: y = {(width+1){1'bz}};
    endcase
end
endmodule

mux21_tb.v
`timescale 1ns/1ps
module mux21_tb();
localparam width_tb = 5;
reg [width_tb-1:0] a_tb, b_tb;
reg sel_tb;
wire [width_tb-1:0]y_op;
mux21 #(.width(width_tb)) DUT(
    .a(a_tb),
    .b(b_tb),
    .sel(sel_tb),
    .y(y_op)
);
initial begin
    $dumpfile("sim.vcd");
    $dumpvars(0,mux21_tb);
    $monitor ("Time:%0t | sel = %b |a = %b  b = %b | y = %b", $time, sel_tb ,a_tb, b_tb, y_op);
    sel_tb = 1'b0; a_tb = 5'b00000; b_tb = 5'b00000; #10;
    sel_tb = 1'b0; a_tb = 5'b00000; b_tb = 5'b00001; #10;
    sel_tb = 1'b0; a_tb = 5'b00001; b_tb = 5'b00000; #10;
    sel_tb = 1'b0; a_tb = 5'b00001; b_tb = 5'b00001; #10;

    sel_tb = 1'b1; a_tb = 5'b00000; b_tb = 5'b00000; #10;
    sel_tb = 1'b1; a_tb = 5'b00000; b_tb = 5'b00001; #10;
    sel_tb = 1'b1; a_tb = 5'b00001; b_tb = 5'b00000; #10;
    sel_tb = 1'b1; a_tb = 5'b00001; b_tb = 5'b00001; #10;

    $finish;
end
endmodule

sim.vcd
$date
	Fri Mar 20 00:16:14 2026
$end
$version
	Icarus Verilog
$end
$timescale
	1ps
$end
$scope module mux21_tb $end
$var wire 5 ! y_op [4:0] $end
$var parameter 32 " width_tb $end
$var reg 5 # a_tb [4:0] $end
$var reg 5 $ b_tb [4:0] $end
$var reg 1 % sel_tb $end
$scope module DUT $end
$var wire 5 & a [4:0] $end
$var wire 5 ' b [4:0] $end
$var wire 1 % sel $end
$var parameter 32 ( width $end
$var reg 5 ) y [4:0] $end
$upscope $end
$upscope $end
$enddefinitions $end
$comment Show the parameter values. $end
$dumpall
b101 (
b101 "
$end
#0
$dumpvars
b0 )
b0 '
b0 &
0%
b0 $
b0 #
b0 !
$end
#10000
b1 $
b1 '
#20000
b1 !
b1 )
b0 $
b0 '
b1 #
b1 &
#30000
b1 $
b1 '
#40000
b0 !
b0 )
b0 $
b0 '
b0 #
b0 &
1%
#50000
b1 !
b1 )
b1 $
b1 '
#60000
b0 !
b0 )
b0 $
b0 '
b1 #
b1 &
#70000
b1 !
b1 )
b1 $
b1 '
